{
  "best_metric": null,
  "best_model_checkpoint": null,
  "epoch": 0.2,
  "eval_steps": 500,
  "global_step": 50,
  "is_hyper_param_search": false,
  "is_local_process_zero": true,
  "is_world_process_zero": true,
  "log_history": [
    {
      "epoch": 0.02,
      "grad_norm": 41.8588752746582,
      "learning_rate": 5e-05,
      "loss": 5.1526,
      "step": 5
    },
    {
      "epoch": 0.04,
      "grad_norm": 4.330800533294678,
      "learning_rate": 0.0001,
      "loss": 4.854,
      "step": 10
    },
    {
      "epoch": 0.06,
      "grad_norm": 40.254756927490234,
      "learning_rate": 0.00015000000000000001,
      "loss": 4.6478,
      "step": 15
    },
    {
      "epoch": 0.08,
      "grad_norm": 17.184343338012695,
      "learning_rate": 0.0002,
      "loss": 2.7908,
      "step": 20
    },
    {
      "epoch": 0.1,
      "grad_norm": 7.647662162780762,
      "learning_rate": 0.0001875,
      "loss": 1.9907,
      "step": 25
    },
    {
      "epoch": 0.12,
      "grad_norm": 5.243800640106201,
      "learning_rate": 0.000175,
      "loss": 1.611,
      "step": 30
    },
    {
      "epoch": 0.14,
      "grad_norm": 1.9426788091659546,
      "learning_rate": 0.00016250000000000002,
      "loss": 1.0505,
      "step": 35
    },
    {
      "epoch": 0.16,
      "grad_norm": 0.8215962052345276,
      "learning_rate": 0.00015000000000000001,
      "loss": 1.0657,
      "step": 40
    },
    {
      "epoch": 0.18,
      "grad_norm": 0.43153950572013855,
      "learning_rate": 0.0001375,
      "loss": 0.9945,
      "step": 45
    },
    {
      "epoch": 0.2,
      "grad_norm": 0.5436094403266907,
      "learning_rate": 0.000125,
      "loss": 1.0855,
      "step": 50
    }
  ],
  "logging_steps": 5,
  "max_steps": 100,
  "num_input_tokens_seen": 0,
  "num_train_epochs": 1,
  "save_steps": 50,
  "stateful_callbacks": {
    "TrainerControl": {
      "args": {
        "should_epoch_stop": false,
        "should_evaluate": false,
        "should_log": false,
        "should_save": true,
        "should_training_stop": false
      },
      "attributes": {}
    }
  },
  "total_flos": 636545610547200.0,
  "train_batch_size": 1,
  "trial_name": null,
  "trial_params": null
}
